gob/gob.py
gob/__init__.py
gob/metrics/__init__.py
gob/metrics/proportion.py
gob/metrics/metric.py
gob/metrics/f_target.py
gob/utils/print_table.py
gob/utils/__init__.py
gob/optimizers/__init__.py
gob/optimizers/optimizer.py
gob/optimizers/cpp_optimizers.cpython-313-darwin.so
gob/optimizers/misc/CMA_ES.py
gob/optimizers/misc/BayesOpt.py
gob/optimizers/misc/CRS.py
gob/optimizers/misc/GD.py
gob/optimizers/misc/Direct.py
gob/optimizers/misc/MLSL.py
gob/optimizers/misc/PRS.py
gob/optimizers/particles/SBS.py
gob/optimizers/particles/Langevin.py
gob/optimizers/particles/CBO.py
gob/optimizers/particles/PSO.py
gob/optimizers/decision/ECP.py
gob/optimizers/decision/AdaRankOpt.py
gob/optimizers/decision/AdaLIPO_P.py
gob/optimizers/cpp_optimizers/CMakeLists.txt
gob/optimizers/cpp_optimizers/cpp_optimizers.cc
gob/optimizers/cpp_optimizers/cpp_optimizers.pyx
gob/optimizers/cpp_optimizers/glpk-5.0/install-sh
gob/optimizers/cpp_optimizers/glpk-5.0/configure.ac
gob/optimizers/cpp_optimizers/glpk-5.0/INSTALL
gob/optimizers/cpp_optimizers/glpk-5.0/ltmain.sh
gob/optimizers/cpp_optimizers/glpk-5.0/configure
gob/optimizers/cpp_optimizers/glpk-5.0/ChangeLog
gob/optimizers/cpp_optimizers/glpk-5.0/AUTHORS
gob/optimizers/cpp_optimizers/glpk-5.0/config.h.in
gob/optimizers/cpp_optimizers/glpk-5.0/config.guess
gob/optimizers/cpp_optimizers/glpk-5.0/depcomp
gob/optimizers/cpp_optimizers/glpk-5.0/setup.job
gob/optimizers/cpp_optimizers/glpk-5.0/missing
gob/optimizers/cpp_optimizers/glpk-5.0/README
gob/optimizers/cpp_optimizers/glpk-5.0/Makefile.am
gob/optimizers/cpp_optimizers/glpk-5.0/config.sub
gob/optimizers/cpp_optimizers/glpk-5.0/COPYING
gob/optimizers/cpp_optimizers/glpk-5.0/NEWS
gob/optimizers/cpp_optimizers/glpk-5.0/THANKS
gob/optimizers/cpp_optimizers/glpk-5.0/Makefile.in
gob/optimizers/cpp_optimizers/glpk-5.0/aclocal.m4
gob/optimizers/cpp_optimizers/glpk-5.0/autogen.sh
gob/optimizers/cpp_optimizers/glpk-5.0/w32/Build_GLPK_with_VC10.bat
gob-0.0.5.dist-info/RECORD
gob-0.0.5.dist-info/WHEEL
gob-0.0.5.dist-info/top_level.txt
gob-0.0.5.dist-info/METADATA
gob-0.0.5.dist-info/licenses/LICENSE
