Metadata-Version: 2.1
Name: gob
Version: 0.0.5
Summary: A collection of global optimization algorithms implemented in C++ and linked with Python.
Author-email: Gaëtan Serré <gaetan.serre@ens-paris-saclay.fr>
Maintainer-email: Gaëtan Serré <gaetan.serre@ens-paris-saclay.fr>
Project-URL: Repository, https://github.com/gaetanserre/GOB
License-File: LICENSE
Requires-Dist: numpy>=2.1.3
Requires-Dist: Cython>=3.0.11
Requires-Dist: nlopt>=2.9.1
Requires-Dist: prettytable>=3.16.0
Requires-Dist: bayesian-optimization>=3.1.0
Requires-Dist: packaging>=25
Requires-Dist: gkls>=1.0.2
